mpu9250_jmdev/__init__.py
mpu9250_jmdev/fake_smbus.py
mpu9250_jmdev/mpu_9250.py
mpu9250_jmdev/registers.py
mpu9250_jmdev-1.0.12.dist-info/LICENSE
mpu9250_jmdev-1.0.12.dist-info/METADATA
mpu9250_jmdev-1.0.12.dist-info/WHEEL
mpu9250_jmdev-1.0.12.dist-info/top_level.txt
mpu9250_jmdev-1.0.12.dist-info/RECORD
