Metadata-Version: 2.1
Name: mpu9250_jmdev
Version: 1.0.12
Summary: MPU-9250 (MPU-6500 + AK8963) I2C Driver in Python for Raspbery PI
Home-page: https://github.com/Intelligent-Vehicle-Perception/MPU-9250-Sensors-Data-Collect
Author: Jeferson Menegazzo
Author-email: jef.menegazzo@outlook.com
License: UNKNOWN
Platform: UNKNOWN
Classifier: Programming Language :: Python :: 3
Classifier: License :: OSI Approved :: MIT License
Classifier: Operating System :: OS Independent
Requires-Python: >=3.6
